auth0_component/__init__.py
auth0_component/frontend/dist/index.html
auth0_component/frontend/dist/assets/index.5223bee9.css
auth0_component/frontend/dist/assets/index.db5f4801.js
streamlit_auth0_component_patch-0.2.1.dist-info/LICENSE
streamlit_auth0_component_patch-0.2.1.dist-info/METADATA
streamlit_auth0_component_patch-0.2.1.dist-info/WHEEL
streamlit_auth0_component_patch-0.2.1.dist-info/top_level.txt
streamlit_auth0_component_patch-0.2.1.dist-info/RECORD
