Metadata-Version: 2.1
Name: streamlit-auth0-component-patch
Version: 0.2.1
Summary: UNKNOWN
Home-page: UNKNOWN
Author: 
Author-email: 
License: UNKNOWN
Platform: UNKNOWN
Requires-Python: >=3.6
License-File: LICENSE
Requires-Dist: streamlit (>=0.63)
Requires-Dist: python-jose (==3.3.0)
